setup.cfg
setup.py
TOPSIS_AbhimanyuParashar_101816011.egg-info/PKG-INFO
TOPSIS_AbhimanyuParashar_101816011.egg-info/SOURCES.txt
TOPSIS_AbhimanyuParashar_101816011.egg-info/dependency_links.txt
TOPSIS_AbhimanyuParashar_101816011.egg-info/entry_points.txt
TOPSIS_AbhimanyuParashar_101816011.egg-info/requires.txt
TOPSIS_AbhimanyuParashar_101816011.egg-info/top_level.txt
source/Topsis.py